cyanobot/Adapter.py
cyanobot/Bot.py
cyanobot/Logger.py
cyanobot/Plugins.py
cyanobot/__init__.py
cyanobot/cb.py
cyanobot-0.0.1.7.dist-info/METADATA
cyanobot-0.0.1.7.dist-info/WHEEL
cyanobot-0.0.1.7.dist-info/top_level.txt
cyanobot-0.0.1.7.dist-info/RECORD
