Metadata-Version: 2.1
Name: cyanobot
Version: 0.0.1.7
Summary: A simple bot framework
Home-page: UNKNOWN
Author: cyanobird
Author-email: 3358851903@qq.com
License: UNKNOWN
Platform: all
Requires-Dist: pyfiglet
